jeevescli/__init__.py
jeevescli/base_cli.py
jeevescli/commands.py
jeevescli/config.py
jeevescli/diff_utils.py
jeevescli/jeeves.py
jeevescli/terminal_tool.py
jeevescli/tools.py
jeevescli-0.1.0.dist-info/METADATA
jeevescli-0.1.0.dist-info/WHEEL
jeevescli-0.1.0.dist-info/entry_points.txt
jeevescli-0.1.0.dist-info/top_level.txt
jeevescli-0.1.0.dist-info/RECORD
