Metadata-Version: 2.4
Name: jeevescli
Version: 0.1.0
Summary: Stateless, small context, high leverage AI assistant
Home-page: https://github.com/dadukhankevin/jeevescli
Author: Daniel Losey
Project-URL: Homepage, https://github.com/dadukhankevin/jeevescli
Project-URL: Bug Reports, https://github.com/dadukhankevin/jeevescli/issues
Project-URL: Source, https://github.com/dadukhankevin/jeevescli
Keywords: ai,assistant,cli,developer,tools
Classifier: Development Status :: 3 - Alpha
Classifier: Intended Audience :: Developers
Classifier: License :: OSI Approved :: MIT License
Classifier: Operating System :: OS Independent
Classifier: Programming Language :: Python :: 3
Classifier: Programming Language :: Python :: 3.8
Classifier: Programming Language :: Python :: 3.9
Classifier: Programming Language :: Python :: 3.10
Classifier: Programming Language :: Python :: 3.11
Classifier: Programming Language :: Python :: 3.12
Classifier: Topic :: Utilities
Requires-Python: >=3.8
Requires-Dist: openai
Requires-Dist: pydantic
Requires-Dist: python-dotenv
Requires-Dist: pysublime
Requires-Dist: flask
Dynamic: home-page
Dynamic: requires-python
